navigation_vis/AbstractView.py
navigation_vis/GridSpec.py
navigation_vis/Raster.py
navigation_vis/__init__.py
navigation_vis/_version.py
navigation_vis-0.9.dist-info/LICENSE
navigation_vis-0.9.dist-info/METADATA
navigation_vis-0.9.dist-info/WHEEL
navigation_vis-0.9.dist-info/top_level.txt
navigation_vis-0.9.dist-info/RECORD
