Metadata-Version: 2.1
Name: navigation-vis
Version: 0.9
Summary: A lightweight library for visualizing navigation grid world
Home-page: https://github.com/yrevar/navigation_vis
Author: Yagnesh Revar
Author-email: mailto.yagnesh+github@gmail.com
License: UNKNOWN
Keywords: Markov Decision Process,MDP,Navigation,Data Visualization
Platform: UNKNOWN
Classifier: Programming Language :: Python :: 3
Classifier: License :: OSI Approved :: Apache Software License
Classifier: Operating System :: OS Independent
Requires-Python: >=3.6
